multi_label_pigeon/__init__.py
multi_label_pigeon/__version__.py
multi_label_pigeon/annotate.py
multi_label_pigeon_jupyter-0.1.0.dist-info/METADATA
multi_label_pigeon_jupyter-0.1.0.dist-info/RECORD
multi_label_pigeon_jupyter-0.1.0.dist-info/WHEEL
multi_label_pigeon_jupyter-0.1.0.dist-info/top_level.txt
