Metadata-Version: 2.1
Name: multi-label-pigeon-jupyter
Version: 0.1.0
Summary: A way to label multi label image datasets in jupyter
Home-page: https://https://github.com/sugi-chan/multi_label_pigeon
Author: Michael Sugimura
Author-email: deepak.kumar.iet@gmail.com
License: UNKNOWN
Platform: UNKNOWN
Classifier: Programming Language :: Python :: 3
Classifier: License :: OSI Approved :: MIT License
Classifier: Operating System :: OS Independent
